README.md
setup.py
awsi/__init__.py
awsi/awsi.py
awsi.egg-info/PKG-INFO
awsi.egg-info/SOURCES.txt
awsi.egg-info/dependency_links.txt
awsi.egg-info/entry_points.txt
awsi.egg-info/not-zip-safe
awsi.egg-info/requires.txt
awsi.egg-info/top_level.txt