Metadata-Version: 2.1
Name: awsi
Version: 1.5.3
Summary: AWS EC2 information and connection tool
Home-page: http://github.com/cuotos/awsi
Author: Dan Potepa
Author-email: dan@danpotepa.co.uk
License: wtfpl
Platform: UNKNOWN
Classifier: Programming Language :: Python :: 2.7
Classifier: Topic :: Utilities
